{"Optimal": {"uncertain1.json": 0.16666667, "uncertain1015.json": 0.30940989, "uncertain1338.json": 0.4755549, "uncertain1365.json": 0.11488084, "uncertain2.json": 0.6, "uncertain3.json": 0.36754447, "uncertain373.json": 0.89654683, "uncertain4.json": 0.0, "uncertain40.json": 0.080454097, "uncertain403.json": 0.96891544, "uncertain537.json": 0.15574749, "uncertain600.json": 0.98630377}, "Invalid": [], "Infeasible": ["uncertain10.json", "uncertain100.json", "uncertain1000.json", "uncertain1001.json", "uncertain1002.json", "uncertain1003.json", "uncertain1004.json", "uncertain1005.json", "uncertain1006.json", "uncertain1007.json", "uncertain1008.json", "uncertain1009.json", "uncertain101.json", "uncertain1010.json", "uncertain1011.json", "uncertain1012.json", "uncertain1013.json", "uncertain1014.json", "uncertain1016.json", "uncertain1017.json", "uncertain1018.json", "uncertain1019.json", "uncertain102.json", "uncertain1020.json", "uncertain1021.json", "uncertain1022.json", "uncertain1023.json", "uncertain1024.json", "uncertain1025.json", "uncertain1026.json", "uncertain1027.json", "uncertain1028.json", "uncertain1029.json", "uncertain103.json", "uncertain1030.json", "uncertain1031.json", "uncertain1032.json", "uncertain1033.json", "uncertain1034.json", "uncertain1035.json", "uncertain1036.json", "uncertain1037.json", "uncertain1038.json", "uncertain1039.json", "uncertain104.json", "uncertain1040.json", "uncertain1041.json", "uncertain1042.json", "uncertain1043.json", "uncertain1044.json", "uncertain1045.json", "uncertain1046.json", "uncertain1047.json", "uncertain1048.json", "uncertain1049.json", "uncertain105.json", "uncertain1050.json", "uncertain1051.json", "uncertain1052.json", "uncertain1053.json", "uncertain1054.json", "uncertain1055.json", "uncertain1056.json", "uncertain1057.json", "uncertain1058.json", "uncertain1059.json", "uncertain106.json", "uncertain1060.json", "uncertain1061.json", "uncertain1062.json", "uncertain1063.json", "uncertain1064.json", "uncertain1065.json", "uncertain1066.json", "uncertain1067.json", "uncertain1068.json", "uncertain1069.json", "uncertain107.json", "uncertain1070.json", "uncertain1071.json", "uncertain1072.json", "uncertain1073.json", "uncertain1074.json", "uncertain1075.json", "uncertain1076.json", "uncertain1077.json", "uncertain1078.json", "uncertain1079.json", "uncertain108.json", "uncertain1080.json", "uncertain1081.json", "uncertain1082.json", "uncertain1083.json", "uncertain1084.json", "uncertain1085.json", "uncertain1086.json", "uncertain1087.json", "uncertain1088.json", "uncertain1089.json", "uncertain109.json", "uncertain1090.json", "uncertain1091.json", "uncertain1092.json", "uncertain1093.json", "uncertain1094.json", "uncertain1095.json", "uncertain1096.json", "uncertain1097.json", "uncertain1098.json", "uncertain1099.json", "uncertain11.json", "uncertain110.json", "uncertain1100.json", "uncertain1101.json", "uncertain1102.json", "uncertain1103.json", "uncertain1104.json", "uncertain1105.json", "uncertain1106.json", "uncertain1107.json", "uncertain1108.json", "uncertain1109.json", "uncertain111.json", "uncertain1110.json", "uncertain1111.json", "uncertain1112.json", "uncertain1113.json", "uncertain1114.json", "uncertain1115.json", "uncertain1116.json", "uncertain1117.json", "uncertain1118.json", "uncertain1119.json", "uncertain112.json", "uncertain1120.json", "uncertain1121.json", "uncertain1122.json", "uncertain1123.json", "uncertain1124.json", "uncertain1125.json", "uncertain1126.json", "uncertain1127.json", "uncertain1128.json", "uncertain1129.json", "uncertain113.json", "uncertain1130.json", "uncertain1131.json", "uncertain1132.json", "uncertain1133.json", "uncertain1134.json", "uncertain1135.json", "uncertain1136.json", "uncertain1137.json", "uncertain1138.json", "uncertain1139.json", "uncertain114.json", "uncertain1140.json", "uncertain1141.json", "uncertain1142.json", "uncertain1143.json", "uncertain1144.json", "uncertain1145.json", "uncertain1146.json", "uncertain1147.json", "uncertain1148.json", "uncertain1149.json", "uncertain115.json", "uncertain1150.json", "uncertain1151.json", "uncertain1152.json", "uncertain1153.json", "uncertain1154.json", "uncertain1155.json", "uncertain1156.json", "uncertain1157.json", "uncertain1158.json", "uncertain1159.json", "uncertain116.json", "uncertain1160.json", "uncertain1161.json", "uncertain1162.json", "uncertain1163.json", "uncertain1164.json", "uncertain1165.json", "uncertain1166.json", "uncertain1167.json", "uncertain1168.json", "uncertain1169.json", "uncertain117.json", "uncertain1170.json", "uncertain1171.json", "uncertain1172.json", "uncertain1173.json", "uncertain1174.json", "uncertain1175.json", "uncertain1176.json", "uncertain1177.json", "uncertain1178.json", "uncertain1179.json", "uncertain118.json", "uncertain1180.json", "uncertain1181.json", "uncertain1182.json", "uncertain1183.json", "uncertain1184.json", "uncertain1185.json", "uncertain1186.json", "uncertain1187.json", "uncertain1188.json", "uncertain1189.json", "uncertain119.json", "uncertain1190.json", "uncertain1191.json", "uncertain1192.json", "uncertain1193.json", "uncertain1194.json", "uncertain1195.json", "uncertain1196.json", "uncertain1197.json", "uncertain1198.json", "uncertain1199.json", "uncertain12.json", "uncertain120.json", "uncertain1200.json", "uncertain1201.json", "uncertain1202.json", "uncertain1203.json", "uncertain1204.json", "uncertain1205.json", "uncertain1206.json", "uncertain1207.json", "uncertain1208.json", "uncertain1209.json", "uncertain121.json", "uncertain1210.json", "uncertain1211.json", "uncertain1212.json", "uncertain1213.json", "uncertain1214.json", "uncertain1215.json", "uncertain1216.json", "uncertain1217.json", "uncertain1218.json", "uncertain1219.json", "uncertain122.json", "uncertain1220.json", "uncertain1221.json", "uncertain1222.json", "uncertain1223.json", "uncertain1224.json", "uncertain1225.json", "uncertain1226.json", "uncertain1227.json", "uncertain1228.json", "uncertain1229.json", "uncertain123.json", "uncertain1230.json", "uncertain1231.json", "uncertain1232.json", "uncertain1233.json", "uncertain1234.json", "uncertain1235.json", "uncertain1236.json", "uncertain1237.json", "uncertain1238.json", "uncertain1239.json", "uncertain124.json", "uncertain1240.json", "uncertain1241.json", "uncertain1242.json", "uncertain1243.json", "uncertain1244.json", "uncertain1245.json", "uncertain1246.json", "uncertain1247.json", "uncertain1248.json", "uncertain1249.json", "uncertain125.json", "uncertain1250.json", "uncertain1251.json", "uncertain1252.json", "uncertain1253.json", "uncertain1254.json", "uncertain1255.json", "uncertain1256.json", "uncertain1257.json", "uncertain1258.json", "uncertain1259.json", "uncertain126.json", "uncertain1260.json", "uncertain1261.json", "uncertain1262.json", "uncertain1263.json", "uncertain1264.json", "uncertain1265.json", "uncertain1266.json", "uncertain1267.json", "uncertain1268.json", "uncertain1269.json", "uncertain127.json", "uncertain1270.json", "uncertain1271.json", "uncertain1272.json", "uncertain1273.json", "uncertain1274.json", "uncertain1275.json", "uncertain1276.json", "uncertain1277.json", "uncertain1278.json", "uncertain1279.json", "uncertain128.json", "uncertain1280.json", "uncertain1281.json", "uncertain1282.json", "uncertain1283.json", "uncertain1284.json", "uncertain1285.json", "uncertain1286.json", "uncertain1287.json", "uncertain1288.json", "uncertain1289.json", "uncertain129.json", "uncertain1290.json", "uncertain1291.json", "uncertain1292.json", "uncertain1293.json", "uncertain1294.json", "uncertain1295.json", "uncertain1296.json", "uncertain1297.json", "uncertain1298.json", "uncertain1299.json", "uncertain13.json", "uncertain130.json", "uncertain1300.json", "uncertain1301.json", "uncertain1302.json", "uncertain1303.json", "uncertain1304.json", "uncertain1305.json", "uncertain1306.json", "uncertain1307.json", "uncertain1308.json", "uncertain1309.json", "uncertain131.json", "uncertain1310.json", "uncertain1311.json", "uncertain1312.json", "uncertain1313.json", "uncertain1314.json", "uncertain1315.json", "uncertain1316.json", "uncertain1317.json", "uncertain1318.json", "uncertain1319.json", "uncertain132.json", "uncertain1320.json", "uncertain1321.json", "uncertain1322.json", "uncertain1323.json", "uncertain1324.json", "uncertain1325.json", "uncertain1326.json", "uncertain1327.json", "uncertain1328.json", "uncertain1329.json", "uncertain133.json", "uncertain1330.json", "uncertain1331.json", "uncertain1332.json", "uncertain1333.json", "uncertain1334.json", "uncertain1335.json", "uncertain1336.json", "uncertain1337.json", "uncertain1339.json", "uncertain134.json", "uncertain1340.json", "uncertain1341.json", "uncertain1342.json", "uncertain1343.json", "uncertain1344.json", "uncertain1345.json", "uncertain1346.json", "uncertain1347.json", "uncertain1348.json", "uncertain1349.json", "uncertain135.json", "uncertain1350.json", "uncertain1351.json", "uncertain1352.json", "uncertain1353.json", "uncertain1354.json", "uncertain1355.json", "uncertain1356.json", "uncertain1357.json", "uncertain1358.json", "uncertain1359.json", "uncertain136.json", "uncertain1360.json", "uncertain1361.json", "uncertain1362.json", "uncertain1363.json", "uncertain1364.json", "uncertain1366.json", "uncertain1367.json", "uncertain1368.json", "uncertain1369.json", "uncertain137.json", "uncertain1370.json", "uncertain1371.json", "uncertain1372.json", "uncertain1373.json", "uncertain1374.json", "uncertain1375.json", "uncertain1376.json", "uncertain1377.json", "uncertain1378.json", "uncertain1379.json", "uncertain138.json", "uncertain1380.json", "uncertain1381.json", "uncertain1382.json", "uncertain1383.json", "uncertain1384.json", "uncertain1385.json", "uncertain1386.json", "uncertain1387.json", "uncertain1388.json", "uncertain1389.json", "uncertain139.json", "uncertain1390.json", "uncertain1391.json", "uncertain1392.json", "uncertain1393.json", "uncertain1394.json", "uncertain1395.json", "uncertain1396.json", "uncertain1397.json", "uncertain1398.json", "uncertain1399.json", "uncertain14.json", "uncertain140.json", "uncertain1400.json", "uncertain1401.json", "uncertain1402.json", "uncertain1403.json", "uncertain1404.json", "uncertain1405.json", "uncertain1406.json", "uncertain1407.json", "uncertain1408.json", "uncertain1409.json", "uncertain141.json", "uncertain1410.json", "uncertain1411.json", "uncertain1412.json", "uncertain1413.json", "uncertain1414.json", "uncertain1415.json", "uncertain1416.json", "uncertain1417.json", "uncertain1418.json", "uncertain1419.json", "uncertain142.json", "uncertain1420.json", "uncertain1421.json", "uncertain1422.json", "uncertain1423.json", "uncertain1424.json", "uncertain1425.json", "uncertain1426.json", "uncertain1427.json", "uncertain1428.json", "uncertain1429.json", "uncertain143.json", "uncertain1430.json", "uncertain1431.json", "uncertain1432.json", "uncertain1433.json", "uncertain1434.json", "uncertain1435.json", "uncertain1436.json", "uncertain1437.json", "uncertain1438.json", "uncertain1439.json", "uncertain144.json", "uncertain1440.json", "uncertain1441.json", "uncertain1442.json", "uncertain1443.json", "uncertain1444.json", "uncertain1445.json", "uncertain1446.json", "uncertain1447.json", "uncertain1448.json", "uncertain1449.json", "uncertain145.json", "uncertain1450.json", "uncertain1451.json", "uncertain1452.json", "uncertain1453.json", "uncertain1454.json", "uncertain1455.json", "uncertain1456.json", "uncertain1457.json", "uncertain1458.json", "uncertain1459.json", "uncertain146.json", "uncertain1460.json", "uncertain1461.json", "uncertain1462.json", "uncertain1463.json", "uncertain1464.json", "uncertain147.json", "uncertain148.json", "uncertain149.json", "uncertain15.json", "uncertain150.json", "uncertain151.json", "uncertain152.json", "uncertain153.json", "uncertain154.json", "uncertain155.json", "uncertain156.json", "uncertain157.json", "uncertain158.json", "uncertain159.json", "uncertain16.json", "uncertain160.json", "uncertain161.json", "uncertain162.json", "uncertain163.json", "uncertain164.json", "uncertain165.json", "uncertain166.json", "uncertain167.json", "uncertain168.json", "uncertain169.json", "uncertain17.json", "uncertain170.json", "uncertain171.json", "uncertain172.json", "uncertain173.json", "uncertain174.json", "uncertain175.json", "uncertain176.json", "uncertain177.json", "uncertain178.json", "uncertain179.json", "uncertain18.json", "uncertain180.json", "uncertain181.json", "uncertain182.json", "uncertain183.json", "uncertain184.json", "uncertain185.json", "uncertain186.json", "uncertain187.json", "uncertain188.json", "uncertain189.json", "uncertain19.json", "uncertain190.json", "uncertain191.json", "uncertain192.json", "uncertain193.json", "uncertain194.json", "uncertain195.json", "uncertain196.json", "uncertain197.json", "uncertain198.json", "uncertain199.json", "uncertain20.json", "uncertain200.json", "uncertain201.json", "uncertain202.json", "uncertain203.json", "uncertain204.json", "uncertain205.json", "uncertain206.json", "uncertain207.json", "uncertain208.json", "uncertain209.json", "uncertain21.json", "uncertain210.json", "uncertain211.json", "uncertain212.json", "uncertain213.json", "uncertain214.json", "uncertain215.json", "uncertain216.json", "uncertain217.json", "uncertain218.json", "uncertain219.json", "uncertain22.json", "uncertain220.json", "uncertain221.json", "uncertain222.json", "uncertain223.json", "uncertain224.json", "uncertain225.json", "uncertain226.json", "uncertain227.json", "uncertain228.json", "uncertain229.json", "uncertain23.json", "uncertain230.json", "uncertain231.json", "uncertain232.json", "uncertain233.json", "uncertain234.json", "uncertain235.json", "uncertain236.json", "uncertain237.json", "uncertain238.json", "uncertain239.json", "uncertain24.json", "uncertain240.json", "uncertain241.json", "uncertain242.json", "uncertain243.json", "uncertain244.json", "uncertain245.json", "uncertain246.json", "uncertain247.json", "uncertain248.json", "uncertain249.json", "uncertain25.json", "uncertain250.json", "uncertain251.json", "uncertain252.json", "uncertain253.json", "uncertain254.json", "uncertain255.json", "uncertain256.json", "uncertain257.json", "uncertain258.json", "uncertain259.json", "uncertain26.json", "uncertain260.json", "uncertain261.json", "uncertain262.json", "uncertain263.json", "uncertain264.json", "uncertain265.json", "uncertain266.json", "uncertain267.json", "uncertain268.json", "uncertain269.json", "uncertain27.json", "uncertain270.json", "uncertain271.json", "uncertain272.json", "uncertain273.json", "uncertain274.json", "uncertain275.json", "uncertain276.json", "uncertain277.json", "uncertain278.json", "uncertain279.json", "uncertain28.json", "uncertain280.json", "uncertain281.json", "uncertain282.json", "uncertain283.json", "uncertain284.json", "uncertain285.json", "uncertain286.json", "uncertain287.json", "uncertain288.json", "uncertain289.json", "uncertain29.json", "uncertain290.json", "uncertain291.json", "uncertain292.json", "uncertain293.json", "uncertain294.json", "uncertain295.json", "uncertain296.json", "uncertain297.json", "uncertain298.json", "uncertain299.json", "uncertain30.json", "uncertain300.json", "uncertain301.json", "uncertain302.json", "uncertain303.json", "uncertain304.json", "uncertain305.json", "uncertain306.json", "uncertain307.json", "uncertain308.json", "uncertain309.json", "uncertain31.json", "uncertain310.json", "uncertain311.json", "uncertain312.json", "uncertain313.json", "uncertain314.json", "uncertain315.json", "uncertain316.json", "uncertain317.json", "uncertain318.json", "uncertain319.json", "uncertain32.json", "uncertain320.json", "uncertain321.json", "uncertain322.json", "uncertain323.json", "uncertain324.json", "uncertain325.json", "uncertain326.json", "uncertain327.json", "uncertain328.json", "uncertain329.json", "uncertain33.json", "uncertain330.json", "uncertain331.json", "uncertain332.json", "uncertain333.json", "uncertain334.json", "uncertain335.json", "uncertain336.json", "uncertain337.json", "uncertain338.json", "uncertain339.json", "uncertain34.json", "uncertain340.json", "uncertain341.json", "uncertain342.json", "uncertain343.json", "uncertain344.json", "uncertain345.json", "uncertain346.json", "uncertain347.json", "uncertain348.json", "uncertain349.json", "uncertain35.json", "uncertain350.json", "uncertain351.json", "uncertain352.json", "uncertain353.json", "uncertain354.json", "uncertain355.json", "uncertain356.json", "uncertain357.json", "uncertain358.json", "uncertain359.json", "uncertain36.json", "uncertain360.json", "uncertain361.json", "uncertain362.json", "uncertain363.json", "uncertain364.json", "uncertain365.json", "uncertain366.json", "uncertain367.json", "uncertain368.json", "uncertain369.json", "uncertain37.json", "uncertain370.json", "uncertain371.json", "uncertain372.json", "uncertain374.json", "uncertain375.json", "uncertain376.json", "uncertain377.json", "uncertain378.json", "uncertain379.json", "uncertain38.json", "uncertain380.json", "uncertain381.json", "uncertain382.json", "uncertain383.json", "uncertain384.json", "uncertain385.json", "uncertain386.json", "uncertain387.json", "uncertain388.json", "uncertain389.json", "uncertain39.json", "uncertain390.json", "uncertain391.json", "uncertain392.json", "uncertain393.json", "uncertain394.json", "uncertain395.json", "uncertain396.json", "uncertain397.json", "uncertain398.json", "uncertain399.json", "uncertain400.json", "uncertain401.json", "uncertain402.json", "uncertain404.json", "uncertain405.json", "uncertain406.json", "uncertain407.json", "uncertain408.json", "uncertain409.json", "uncertain41.json", "uncertain410.json", "uncertain411.json", "uncertain412.json", "uncertain413.json", "uncertain414.json", "uncertain415.json", "uncertain416.json", "uncertain417.json", "uncertain418.json", "uncertain419.json", "uncertain42.json", "uncertain420.json", "uncertain421.json", "uncertain422.json", "uncertain423.json", "uncertain424.json", "uncertain425.json", "uncertain426.json", "uncertain427.json", "uncertain428.json", "uncertain429.json", "uncertain43.json", "uncertain430.json", "uncertain431.json", "uncertain432.json", "uncertain433.json", "uncertain434.json", "uncertain435.json", "uncertain436.json", "uncertain437.json", "uncertain438.json", "uncertain439.json", "uncertain44.json", "uncertain440.json", "uncertain441.json", "uncertain442.json", "uncertain443.json", "uncertain444.json", "uncertain445.json", "uncertain446.json", "uncertain447.json", "uncertain448.json", "uncertain449.json", "uncertain45.json", "uncertain450.json", "uncertain451.json", "uncertain452.json", "uncertain453.json", "uncertain454.json", "uncertain455.json", "uncertain456.json", "uncertain457.json", "uncertain458.json", "uncertain459.json", "uncertain46.json", "uncertain460.json", "uncertain461.json", "uncertain462.json", "uncertain463.json", "uncertain464.json", "uncertain465.json", "uncertain466.json", "uncertain467.json", "uncertain468.json", "uncertain469.json", "uncertain47.json", "uncertain470.json", "uncertain471.json", "uncertain472.json", "uncertain473.json", "uncertain474.json", "uncertain475.json", "uncertain476.json", "uncertain477.json", "uncertain478.json", "uncertain479.json", "uncertain48.json", "uncertain480.json", "uncertain481.json", "uncertain482.json", "uncertain483.json", "uncertain484.json", "uncertain485.json", "uncertain486.json", "uncertain487.json", "uncertain488.json", "uncertain489.json", "uncertain49.json", "uncertain490.json", "uncertain491.json", "uncertain492.json", "uncertain493.json", "uncertain494.json", "uncertain495.json", "uncertain496.json", "uncertain497.json", "uncertain498.json", "uncertain499.json", "uncertain5.json", "uncertain50.json", "uncertain500.json", "uncertain501.json", "uncertain502.json", "uncertain503.json", "uncertain504.json", "uncertain505.json", "uncertain506.json", "uncertain507.json", "uncertain508.json", "uncertain509.json", "uncertain51.json", "uncertain510.json", "uncertain511.json", "uncertain512.json", "uncertain513.json", "uncertain514.json", "uncertain515.json", "uncertain516.json", "uncertain517.json", "uncertain518.json", "uncertain519.json", "uncertain52.json", "uncertain520.json", "uncertain521.json", "uncertain522.json", "uncertain523.json", "uncertain524.json", "uncertain525.json", "uncertain526.json", "uncertain527.json", "uncertain528.json", "uncertain529.json", "uncertain53.json", "uncertain530.json", "uncertain531.json", "uncertain532.json", "uncertain533.json", "uncertain534.json", "uncertain535.json", "uncertain536.json", "uncertain538.json", "uncertain539.json", "uncertain54.json", "uncertain540.json", "uncertain541.json", "uncertain542.json", "uncertain543.json", "uncertain544.json", "uncertain545.json", "uncertain546.json", "uncertain547.json", "uncertain548.json", "uncertain549.json", "uncertain55.json", "uncertain550.json", "uncertain551.json", "uncertain552.json", "uncertain553.json", "uncertain554.json", "uncertain555.json", "uncertain556.json", "uncertain557.json", "uncertain558.json", "uncertain559.json", "uncertain56.json", "uncertain560.json", "uncertain561.json", "uncertain562.json", "uncertain563.json", "uncertain564.json", "uncertain565.json", "uncertain566.json", "uncertain567.json", "uncertain568.json", "uncertain569.json", "uncertain57.json", "uncertain570.json", "uncertain571.json", "uncertain572.json", "uncertain573.json", "uncertain574.json", "uncertain575.json", "uncertain576.json", "uncertain577.json", "uncertain578.json", "uncertain579.json", "uncertain58.json", "uncertain580.json", "uncertain581.json", "uncertain582.json", "uncertain583.json", "uncertain584.json", "uncertain585.json", "uncertain586.json", "uncertain587.json", "uncertain588.json", "uncertain589.json", "uncertain59.json", "uncertain590.json", "uncertain591.json", "uncertain592.json", "uncertain593.json", "uncertain594.json", "uncertain595.json", "uncertain596.json", "uncertain597.json", "uncertain598.json", "uncertain599.json", "uncertain6.json", "uncertain60.json", "uncertain601.json", "uncertain602.json", "uncertain603.json", "uncertain604.json", "uncertain605.json", "uncertain606.json", "uncertain607.json", "uncertain608.json", "uncertain609.json", "uncertain61.json", "uncertain610.json", "uncertain611.json", "uncertain612.json", "uncertain613.json", "uncertain614.json", "uncertain615.json", "uncertain616.json", "uncertain617.json", "uncertain618.json", "uncertain619.json", "uncertain62.json", "uncertain620.json", "uncertain621.json", "uncertain622.json", "uncertain623.json", "uncertain624.json", "uncertain625.json", "uncertain626.json", "uncertain627.json", "uncertain628.json", "uncertain629.json", "uncertain63.json", "uncertain630.json", "uncertain631.json", "uncertain632.json", "uncertain633.json", "uncertain634.json", "uncertain635.json", "uncertain636.json", "uncertain637.json", "uncertain638.json", "uncertain639.json", "uncertain64.json", "uncertain640.json", "uncertain641.json", "uncertain642.json", "uncertain643.json", "uncertain644.json", "uncertain645.json", "uncertain646.json", "uncertain647.json", "uncertain648.json", "uncertain649.json", "uncertain65.json", "uncertain650.json", "uncertain651.json", "uncertain652.json", "uncertain653.json", "uncertain654.json", "uncertain655.json", "uncertain656.json", "uncertain657.json", "uncertain658.json", "uncertain659.json", "uncertain66.json", "uncertain660.json", "uncertain661.json", "uncertain662.json", "uncertain663.json", "uncertain664.json", "uncertain665.json", "uncertain666.json", "uncertain667.json", "uncertain668.json", "uncertain669.json", "uncertain67.json", "uncertain670.json", "uncertain671.json", "uncertain672.json", "uncertain673.json", "uncertain674.json", "uncertain675.json", "uncertain676.json", "uncertain677.json", "uncertain678.json", "uncertain679.json", "uncertain68.json", "uncertain680.json", "uncertain681.json", "uncertain682.json", "uncertain683.json", "uncertain684.json", "uncertain685.json", "uncertain686.json", "uncertain687.json", "uncertain688.json", "uncertain689.json", "uncertain69.json", "uncertain690.json", "uncertain691.json", "uncertain692.json", "uncertain693.json", "uncertain694.json", "uncertain695.json", "uncertain696.json", "uncertain697.json", "uncertain698.json", "uncertain699.json", "uncertain7.json", "uncertain70.json", "uncertain700.json", "uncertain701.json", "uncertain702.json", "uncertain703.json", "uncertain704.json", "uncertain705.json", "uncertain706.json", "uncertain707.json", "uncertain708.json", "uncertain709.json", "uncertain71.json", "uncertain710.json", "uncertain711.json", "uncertain712.json", "uncertain713.json", "uncertain714.json", "uncertain715.json", "uncertain716.json", "uncertain717.json", "uncertain718.json", "uncertain719.json", "uncertain72.json", "uncertain720.json", "uncertain721.json", "uncertain722.json", "uncertain723.json", "uncertain724.json", "uncertain725.json", "uncertain726.json", "uncertain727.json", "uncertain728.json", "uncertain729.json", "uncertain73.json", "uncertain730.json", "uncertain731.json", "uncertain732.json", "uncertain733.json", "uncertain734.json", "uncertain735.json", "uncertain736.json", "uncertain737.json", "uncertain738.json", "uncertain739.json", "uncertain74.json", "uncertain740.json", "uncertain741.json", "uncertain742.json", "uncertain743.json", "uncertain744.json", "uncertain745.json", "uncertain746.json", "uncertain747.json", "uncertain748.json", "uncertain749.json", "uncertain75.json", "uncertain750.json", "uncertain751.json", "uncertain752.json", "uncertain753.json", "uncertain754.json", "uncertain755.json", "uncertain756.json", "uncertain757.json", "uncertain758.json", "uncertain759.json", "uncertain76.json", "uncertain760.json", "uncertain761.json", "uncertain762.json", "uncertain763.json", "uncertain764.json", "uncertain765.json", "uncertain766.json", "uncertain767.json", "uncertain768.json", "uncertain769.json", "uncertain77.json", "uncertain770.json", "uncertain771.json", "uncertain772.json", "uncertain773.json", "uncertain774.json", "uncertain775.json", "uncertain776.json", "uncertain777.json", "uncertain778.json", "uncertain779.json", "uncertain78.json", "uncertain780.json", "uncertain781.json", "uncertain782.json", "uncertain783.json", "uncertain784.json", "uncertain785.json", "uncertain786.json", "uncertain787.json", "uncertain788.json", "uncertain789.json", "uncertain79.json", "uncertain790.json", "uncertain791.json", "uncertain792.json", "uncertain793.json", "uncertain794.json", "uncertain795.json", "uncertain796.json", "uncertain797.json", "uncertain798.json", "uncertain799.json", "uncertain8.json", "uncertain80.json", "uncertain800.json", "uncertain801.json", "uncertain802.json", "uncertain803.json", "uncertain804.json", "uncertain805.json", "uncertain806.json", "uncertain807.json", "uncertain808.json", "uncertain809.json", "uncertain81.json", "uncertain810.json", "uncertain811.json", "uncertain812.json", "uncertain813.json", "uncertain814.json", "uncertain815.json", "uncertain816.json", "uncertain817.json", "uncertain818.json", "uncertain819.json", "uncertain82.json", "uncertain820.json", "uncertain821.json", "uncertain822.json", "uncertain823.json", "uncertain824.json", "uncertain825.json", "uncertain826.json", "uncertain827.json", "uncertain828.json", "uncertain829.json", "uncertain83.json", "uncertain830.json", "uncertain831.json", "uncertain832.json", "uncertain833.json", "uncertain834.json", "uncertain835.json", "uncertain836.json", "uncertain837.json", "uncertain838.json", "uncertain839.json", "uncertain84.json", "uncertain840.json", "uncertain841.json", "uncertain842.json", "uncertain843.json", "uncertain844.json", "uncertain845.json", "uncertain846.json", "uncertain847.json", "uncertain848.json", "uncertain849.json", "uncertain85.json", "uncertain850.json", "uncertain851.json", "uncertain852.json", "uncertain853.json", "uncertain854.json", "uncertain855.json", "uncertain856.json", "uncertain857.json", "uncertain858.json", "uncertain859.json", "uncertain86.json", "uncertain860.json", "uncertain861.json", "uncertain862.json", "uncertain863.json", "uncertain864.json", "uncertain865.json", "uncertain866.json", "uncertain867.json", "uncertain868.json", "uncertain869.json", "uncertain87.json", "uncertain870.json", "uncertain871.json", "uncertain872.json", "uncertain873.json", "uncertain874.json", "uncertain875.json", "uncertain876.json", "uncertain877.json", "uncertain878.json", "uncertain879.json", "uncertain88.json", "uncertain880.json", "uncertain881.json", "uncertain882.json", "uncertain883.json", "uncertain884.json", "uncertain885.json", "uncertain886.json", "uncertain887.json", "uncertain888.json", "uncertain889.json", "uncertain89.json", "uncertain890.json", "uncertain891.json", "uncertain892.json", "uncertain893.json", "uncertain894.json", "uncertain895.json", "uncertain896.json", "uncertain897.json", "uncertain898.json", "uncertain899.json", "uncertain9.json", "uncertain90.json", "uncertain900.json", "uncertain901.json", "uncertain902.json", "uncertain903.json", "uncertain904.json", "uncertain905.json", "uncertain906.json", "uncertain907.json", "uncertain908.json", "uncertain909.json", "uncertain91.json", "uncertain910.json", "uncertain911.json", "uncertain912.json", "uncertain913.json", "uncertain914.json", "uncertain915.json", "uncertain916.json", "uncertain917.json", "uncertain918.json", "uncertain919.json", "uncertain92.json", "uncertain920.json", "uncertain921.json", "uncertain922.json", "uncertain923.json", "uncertain924.json", "uncertain925.json", "uncertain926.json", "uncertain927.json", "uncertain928.json", "uncertain929.json", "uncertain93.json", "uncertain930.json", "uncertain931.json", "uncertain932.json", "uncertain933.json", "uncertain934.json", "uncertain935.json", "uncertain936.json", "uncertain937.json", "uncertain938.json", "uncertain939.json", "uncertain94.json", "uncertain940.json", "uncertain941.json", "uncertain942.json", "uncertain943.json", "uncertain944.json", "uncertain945.json", "uncertain946.json", "uncertain947.json", "uncertain948.json", "uncertain949.json", "uncertain95.json", "uncertain950.json", "uncertain951.json", "uncertain952.json", "uncertain953.json", "uncertain954.json", "uncertain955.json", "uncertain956.json", "uncertain957.json", "uncertain958.json", "uncertain959.json", "uncertain96.json", "uncertain960.json", "uncertain961.json", "uncertain962.json", "uncertain963.json", "uncertain964.json", "uncertain965.json", "uncertain966.json", "uncertain967.json", "uncertain968.json", "uncertain969.json", "uncertain97.json", "uncertain970.json", "uncertain971.json", "uncertain972.json", "uncertain973.json", "uncertain974.json", "uncertain975.json", "uncertain976.json", "uncertain977.json", "uncertain978.json", "uncertain979.json", "uncertain98.json", "uncertain980.json", "uncertain981.json", "uncertain982.json", "uncertain983.json", "uncertain984.json", "uncertain985.json", "uncertain986.json", "uncertain987.json", "uncertain988.json", "uncertain989.json", "uncertain99.json", "uncertain990.json", "uncertain991.json", "uncertain992.json", "uncertain993.json", "uncertain994.json", "uncertain995.json", "uncertain996.json", "uncertain997.json", "uncertain998.json", "uncertain999.json"], "Unbounded": []}